mistkit/VERSION.py
mistkit/__init__.py
mistkit/code.py
mistkit-0.1.1.dist-info/METADATA
mistkit-0.1.1.dist-info/WHEEL
mistkit-0.1.1.dist-info/licenses/LICENSE.txt
mistkit-0.1.1.dist-info/RECORD
