Metadata-Version: 2.3
Name: mistkit
Version: 0.1.1
Summary: mistkit extends the python3 based qiskit quantum computing language state_drawer function with a misty state output possibility.
Project-URL: Hompage, https://github.com/elmbeech/mistkit
Project-URL: Documentation, https://github.com/elmbeech/mistkit/blob/main/README.md
Project-URL: Issues, https://github.com/elmbeech/mistkit/issues
Project-URL: Source, https://github.com/elmbeech/mistkit
Author-email: Elmar Bucher <epbucher@iu.edu>
Maintainer-email: Elmar Bucher <epbucher@iu.edu>
License-Expression: Apache-2.0
License-File: LICENSE.txt
Keywords: ibm,misty state,python3,q is for quantum,qiskit,quantum computing,quantum theory
Classifier: Development Status :: 3 - Alpha
Classifier: Intended Audience :: Education
Classifier: License :: OSI Approved :: Apache Software License
Classifier: Programming Language :: Python :: 3 :: Only
Classifier: Topic :: Scientific/Engineering
Requires-Python: <4,>=3.8
Requires-Dist: numpy
Requires-Dist: qiskit
